Workbook

Sheet Monthly Analysis
A3: Month_Start | B3: Sum of Revenue
A4: 45658 | B4: 10571.65
A5: 45689 | B5: 12205.04
A6: 45717 | B6: 13718.21
A7: 45748 | B7: 11682.12
A8: 45778 | B8: 9630.19
A9: 45809 | B9: 10458.5
A10: 45839 | B10: 10635.35
A11: 45870 | B11: 12734.57
A12: 45901 | B12: 12110.93
A13: 45931 | B13: 10200.41
A14: 45962 | B14: 10180.52
A15: 45992 | B15: 13032.57
A16: Grand Total | B16: 137160.06

Sheet Regional Analysis
A3: Region | B3: Sum of Revenue
A4: Central | B4: 31586.07
A5: South | B5: 27147.15
A6: East | B6: 26860.27
A7: West | B7: 26401.11
A8: North | B8: 25165.46
A9: Grand Total | B9: 137160.06

Sheet Category Analysis
A3: Category | B3: Sum of Revenue
A4: Furniture | B4: 94507.28
A5: Technology | B5: 35728.54
A6: Office Supplies | B6: 6924.24
A7: Grand Total | B7: 137160.06

Sheet Profit Analysis
A3: Category | B3: Sum of Profit
A4: Furniture | B4: 27258.43
A5: Technology | B5: 9954.98
A6: Office Supplies | B6: 1936.6
A7: Grand Total | B7: 39150.01

Sheet Dashboard
A1: SALES PERFORMANCE DASHBOARD
A2: Sales Overview | 2025 | Excel Data Analytics Project
A7: TOTAL REVENUE | B7: ='Data Checks'!B14 -> 137160.06
A9: TOTAL PROFIT | B9: ='Data Checks'!B16 -> 39150.01
A11: TOTAL ORDERS | B11: ='Data Checks'!B18 -> 500
A13: PROFIT MARGIN | B13: ='Data Checks'!B22 -> 28.543302
A28: BUSINESS INSIGHTS & RECOMMENDATIONS
A29: 1. Overall Performance
A30: The business generated ₹137,160.06 in total revenue and ₹39,150.01 in total profit across 500 orders, achieving an overall profit margin of 28.54%.
A31: 2. Regional Performance
A32: The Central region generated the highest revenue at ₹31,586.07, while the North region generated the lowest at ₹25,165.46. The business could investigate differences in customer demand, product mix, and sales strategies across regions.
A33: 3. Product Category Performance
A34: Furniture contributed the highest revenue (₹94,507.28) and profit (₹27,258.43). Technology ranked second in revenue, while Office Supplies contributed the least revenue and profit.
A35: 4. Monthly Sales Trends
A36: Monthly revenue varied throughout 2025. The business could investigate the reasons for stronger and weaker months to improve sales planning and inventory management.
A37: Recommendations
A38: Investigate successful sales practices in the Central region and evaluate whether they can be applied elsewhere.
A39: Review product-level profit margins before deciding which categories to prioritize.
... A41: Monitor revenue, profit, and profit margin together when evaluating business performance.

Sheet Sales_Data
A1: Order_ID | B1: Order_Date | C1: Month | D1: Month_Start | E1: Region | F1: City | G1: Sales_Rep | H1: Customer_Segment | I1: Category | J1: Product | K1: Quantity | L1: Unit_Price | M1: Discount_Rate | N1: Revenue | O1: Cost | P1: Profit | Q1: Payment_Method
A2: ORD-0001 | B2: 45985 | C2: =TEXT(D2,"mmm yyyy") -> Nov 2025 | D2: =DATE(YEAR(B2),MONTH(B2),1) -> 45962 | E2: Central | F2: Bhopal | G2: Karan Patel | H2: Consumer | I2: Technology | J2: Wireless Mouse | K2: 4 | L2: 23.85 | M2: 0 | N2: 95.4 | O2: 70.69 | P2: 24.71 | Q2: Credit Card
A3: ORD-0002 | B3: 45705 | C3: =TEXT(D3,"mmm yyyy") -> Feb 2025 | D3: =DATE(YEAR(B3),MONTH(B3),1) -> 45689 | E3: Central | F3: Indore | G3: Ananya Rao | H3: Corporate | I3: Technology | J3: Keyboard | K3: 3 | L3: 40.76 | M3: 0 | N3: 122.28 | O3: 89.85 | P3: 32.43 | Q3: Net Banking
A4: ORD-0003 | B4: 45661 | C4: =TEXT(D4,"mmm yyyy") -> Jan 2025 | D4: =DATE(YEAR(B4),MONTH(B4),1) -> 45658 | E4: West | F4: Mumbai | G4: Meera Iyer | H4: Corporate | I4: Technology | J4: Headphones | K4: 2 | L4: 74.74 | M4: 0.05 | N4: 142.01 | O4: 82.31 | P4: 59.7 | Q4: Net Banking
A5: ORD-0004 | B5: 45680 | C5: =TEXT(D5,"mmm yyyy") -> Jan 2025 | D5: =DATE(YEAR(B5),MONTH(B5),1) -> 45658 | E5: East | F5: Guwahati | G5: Meera Iyer | H5: Small Business | I5: Furniture | J5: Filing Cabinet | K5: 3 | L5: 233.96 | M5: 0.1 | N5: 631.69 | O5: 381.57 | P5: 250.12 | Q5: UPI
A6: ORD-0005 | B6: 46018 | C6: =TEXT(D6,"mmm yyyy") -> Dec 2025 | D6: =DATE(YEAR(B6),MONTH(B6),1) -> 45992 | E6: North | F6: Chandigarh | G6: Vikram Singh | H6: Corporate | I6: Technology | J6: Wireless Mouse | K6: 3 | L6: 26.75 | M6: 0 | N6: 80.25 | O6: 62.32 | P6: 17.93 | Q6: Net Banking
A7: ORD-0006 | B7: 45741 | C7: =TEXT(D7,"mmm yyyy") -> Mar 2025 | D7: =DATE(YEAR(B7),MONTH(B7),1) -> 45717 | E7: South | F7: Hyderabad | G7: Ananya Rao | H7: Consumer | I7: Office Supplies | J7: Pens Set | K7: 1 | L7: 9.59 | M7: 0 | N7: 9.59 | O7: 6.74 | P7: 2.85 | Q7: Debit Card
A8: ORD-0007 | B8: 45852 | C8: =TEXT(D8,"mmm yyyy") -> Jul 2025 | D8: =DATE(YEAR(B8),MONTH(B8),1) -> 45839 | E8: North | F8: Chandigarh | G8: Karan Patel | H8: Corporate | I8: Office Supplies | J8: Stapler | K8: 1 | L8: 14.57 | M8: 0 | N8: 14.57 | O8: 8.58 | P8: 5.99 | Q8: Credit Card
A9: ORD-0008 | B9: 45766 | C9: =TEXT(D9,"mmm yyyy") -> Apr 2025 | D9: =DATE(YEAR(B9),MONTH(B9),1) -> 45748 | E9: South | F9: Bengaluru | G9: Vikram Singh | H9: Small Business | I9: Furniture | J9: Bookshelf | K9: 1 | L9: 151.47 | M9: 0.1 | N9: 136.32 | O9: 85.26 | P9: 51.06 | Q9: Debit Card
A10: ORD-0009 | B10: 45956 | C10: =TEXT(D10,"mmm yyyy") -> Oct 2025 | D10: =DATE(YEAR(B10),MONTH(B10),1) -> 45931 | E10: North | F10: Delhi | G10: Rohan Mehta | H10: Small Business | I10: Office Supplies | J10: Pens Set | K10: 1 | L10: 11.19 | M10: 0.15 | N10: 9.51 | O10: 7.48 | P10: 2.03 | Q10: UPI
A11: ORD-0010 | B11: 46006 | C11: =TEXT(D11,"mmm yyyy") -> Dec 2025 | D11: =DATE(YEAR(B11),MONTH(B11),1) -> 45992 | E11: Central | F11: Bhopal | G11: Priya Nair | H11: Small Business | I11: Office Supplies | J11: Stapler | K11: 1 | L11: 14.76 | M11: 0.1 | N11: 13.28 | O11: 10.02 | P11: 3.26 | Q11: Net Banking
A12: ORD-0011 | B12: 45986 | C12: =TEXT(D12,"mmm yyyy") -> Nov 2025 | D12: =DATE(YEAR(B12),MONTH(B12),1) -> 45962 | E12: East | F12: Guwahati | G12: Rohan Mehta | H12: Small Business | I12: Office Supplies | J12: Notebook Pack | K12: 2 | L12: 11.22 | M12: 0 | N12: 22.44 | O12: 18.09 | P12: 4.35 | Q12: Credit Card
A13: ORD-0012 | B13: 45978 | C13: =TEXT(D13,"mmm yyyy") -> Nov 2025 | D13: =DATE(YEAR(B13),MONTH(B13),1) -> 45962 | E13: Central | F13: Bhopal | G13: Meera Iyer | H13: Corporate | I13: Office Supplies | J13: Stapler | K13: 3 | L13: 14 | M13: 0 | N13: 42 | O13: 28.64 | P13: 13.36 | Q13: Credit Card
... A501: ORD-0500 | B501: 45926 | C501: =TEXT(D501,"mmm yyyy") -> Sep 2025 | D501: =DATE(YEAR(B501),MONTH(B501),1) -> 45901 | E501: South | F501: Bengaluru | G501: Aarav Sharma | H501: Corporate | I501: Office Supplies | J501: Pens Set | K501: 1 | L501: 10.92 | M501: 0.15 | N501: 9.28 | O501: 7.9 | P501: 1.38 | Q501: Debit Card

Sheet Data Checks
A1: Duplicates | B1: =COUNTA(Sales_Data!A2:A501)-COUNTA(_xlfn.UNIQUE(Sales_Data!A2:A501)) -> 0
A3: Missing order IDs | B3: =COUNTBLANK(Sales_Data!A2:A501) -> 0
A5: Missing Order Dates | B5: =COUNTBLANK(Sales_Data!B2:B501) -> 0
A7: Missing Regions | B7: =COUNTBLANK(Sales_Data!E2:E501) -> 0
A9: Missing Products | B9: =COUNTBLANK(Sales_Data!J2:J501) -> 0
A11: Missing Revenues | B11: =COUNTBLANK(Sales_Data!N2:N501) -> 0
A14: Total Revenue | B14: =SUM(Sales_Data!N2:N501) -> 137160.06
A16: Total Profit | B16: =SUM(Sales_Data!P2:P501) -> 39150.01
A18: Total Orders | B18: =COUNTA(Sales_Data!A2:A501) -> 500
A20: Total Units Sold | B20: =SUM(Sales_Data!K2:K501) -> 1469
A22: Profit Margin | B22: =(B16/B14)*100 -> 28.543302

Sheet Read_Me
A1: Sales Performance Dashboard — Project Dataset
A2: Purpose | B2: Practice Excel data cleaning, formulas, PivotTables, charts, and an interactive dashboard.
A3: Rows | B3: 500 sales orders (synthetic practice data).
A4: Currency | B4: Indian Rupees (₹). Values are simulated for learning and are not real company records.
A5: Order_ID | B5: Unique identifier for each order.
A6: Order_Date | B6: Date the order was placed.
A7: Region / City | B7: Geographic location of the sale.
A8: Sales_Rep | B8: Representative associated with the order.
A9: Customer_Segment | B9: Consumer, Corporate, or Small Business.
A10: Category / Product | B10: Product grouping and item name.
A11: Quantity | B11: Number of units sold.
A12: Unit_Price | B12: Price per unit before discount.
A13: Discount_Rate | B13: Discount applied to the order.
... A19: Recommended first task | B19: Open Sales_Data, inspect the columns, and save a copy before making changes.
